mkdocs_timetoread_zh/__init__.py
mkdocs_timetoread_zh/plugin.py
mkdocs_timetoread_zh-0.2.0.dist-info/LICENSE
mkdocs_timetoread_zh-0.2.0.dist-info/METADATA
mkdocs_timetoread_zh-0.2.0.dist-info/WHEEL
mkdocs_timetoread_zh-0.2.0.dist-info/entry_points.txt
mkdocs_timetoread_zh-0.2.0.dist-info/RECORD
