Metadata-Version: 2.1
Name: mkdocs-timetoread-zh
Version: 0.2.0
Summary: Estimated Time To Read generator for MkDocs with multiple language support
Home-page: https://github.com/libukai/mkdocs-timetoread-zh
License: MIT
Keywords: mkdocs,plugin,readtime,chinese
Author: Libukai
Author-email: xiaobuyao@gmail.com
Requires-Python: >=3.9
Classifier: License :: OSI Approved :: MIT License
Classifier: Programming Language :: Python :: 3
Classifier: Programming Language :: Python :: 3.9
Classifier: Programming Language :: Python :: 3.10
Classifier: Programming Language :: Python :: 3.11
Classifier: Programming Language :: Python :: 3.12
Requires-Dist: mkdocs (>=1.3)
Project-URL: Repository, https://github.com/libukai/mkdocs-timetoread-zh
